dbnomics_fetcher_ops/__init__.py
dbnomics_fetcher_ops/app_args.py
dbnomics_fetcher_ops/cli.py
dbnomics_fetcher_ops/cli_utils.py
dbnomics_fetcher_ops/file_utils.py
dbnomics_fetcher_ops/format_utils.py
dbnomics_fetcher_ops/gitlab_utils.py
dbnomics_fetcher_ops/loaders.py
dbnomics_fetcher_ops/py.typed
dbnomics_fetcher_ops/ssh.py
dbnomics_fetcher_ops/utils.py
dbnomics_fetcher_ops/commands/__init__.py
dbnomics_fetcher_ops/commands/apply.py
dbnomics_fetcher_ops/commands/clean_workspace.py
dbnomics_fetcher_ops/commands/clean_workspaces.py
dbnomics_fetcher_ops/commands/configure.py
dbnomics_fetcher_ops/commands/list.py
dbnomics_fetcher_ops/commands/prune.py
dbnomics_fetcher_ops/commands/retry.py
dbnomics_fetcher_ops/commands/run.py
dbnomics_fetcher_ops/commands/undeploy.py
dbnomics_fetcher_ops/model/errors.py
dbnomics_fetcher_ops/model/pipelines_config.py
dbnomics_fetcher_ops/model/validators.py
dbnomics_fetcher_ops/model/fetcher_metadata/base.py
dbnomics_fetcher_ops/model/fetcher_metadata/gitlab.py
dbnomics_fetcher_ops/model/pipeline_repo/gitlab.py
dbnomics_fetcher_ops/model/pipeline_repo/in_memory.py
dbnomics_fetcher_ops/model/pipeline_repo/protocol.py
dbnomics_fetcher_ops/services/__init__.py
dbnomics_fetcher_ops/services/clean_pipeline_workspaces.py
dbnomics_fetcher_ops/services/prune_fetcher.py
dbnomics_fetcher_ops/services/retry_fetcher_pipeline_job.py
dbnomics_fetcher_ops/services/run_fetcher_pipeline.py
dbnomics_fetcher_ops-0.6.2.dist-info/METADATA
dbnomics_fetcher_ops-0.6.2.dist-info/WHEEL
dbnomics_fetcher_ops-0.6.2.dist-info/entry_points.txt
dbnomics_fetcher_ops-0.6.2.dist-info/licenses/LICENSE
dbnomics_fetcher_ops-0.6.2.dist-info/RECORD
