Metadata-Version: 2.4
Name: dbnomics_fetcher_ops
Version: 0.6.2
Summary: Manage DBnomics fetchers
Project-URL: Homepage, https://git.nomics.world/dbnomics/dbnomics-fetcher-ops
Project-URL: Bug Tracker, https://git.nomics.world/dbnomics/dbnomics-fetcher-ops/-/issues
Author-email: Christophe Benz <christophe.benz@nomics.world>
License:                     GNU AFFERO GENERAL PUBLIC LICENSE
License-File: LICENSE
Classifier: License :: OSI Approved :: GNU Affero General Public License v3 or later (AGPLv3+)
Classifier: Operating System :: OS Independent
Classifier: Programming Language :: Python :: 3
Requires-Python: >=3.12
Requires-Dist: daiquiri>=3.2.5.1
Requires-Dist: dbnomics-solr>=1.1.19
Requires-Dist: pydantic<2
Requires-Dist: python-dotenv>=1.0.1
Requires-Dist: python-gitlab>=5.0.0
Requires-Dist: pyyaml>=6.0.2
Requires-Dist: requests>=2.32.3
Requires-Dist: typer>=0.12.5
Requires-Dist: validators>=0.34.0
Requires-Dist: xdg>=6.0.0
